{"is_source_file": true, "format": "PHP/HTML", "description": "A PHP script generating an HTML page for a restaurant menu, including database connection, data retrieval, and display of menu items with images.", "external_files": ["https://cdn.jsdelivr.net/npm/bootstrap@5.2.1/dist/css/bootstrap.min.css", "https://cdn.jsdelivr.net/npm/bootstrap-icons@1.10.3/font/bootstrap-icons.css", "https://cdnjs.cloudflare.com/ajax/libs/font-awesome/5.10.0/css/all.min.css", "https://cdn.jsdelivr.net/npm/bootstrap@5.2.1/dist/js/bootstrap.bundle.min.js"], "external_methods": ["mysqli_connect", "mysqli_query", "mysqli_fetch_array", "mysqli_num_rows", "mysqli_connect_error"], "published": ["gridmenu.php"], "classes": [], "methods": [{"name": "mysqli_connect", "description": "Establishes a connection to the MySQL database."}, {"name": "mysqli_query", "description": "Executes a query against the database."}, {"name": "mysqli_fetch_array", "description": "Fetches a result row as an associative array."}, {"name": "mysqli_num_rows", "description": "Returns the number of rows in a result set."}, {"name": "mysqli_connect_error", "description": "Returns the error description from the last connection error."}], "calls": ["mysqli_connect", "mysqli_query", "mysqli_fetch_array", "mysqli_num_rows"], "search-terms": ["PHP restaurant menu", "database connection", "menu display", "base64 image encoding", "spicykitchen database"], "state": 2, "filename": "gridmenu.php", "format-version": 4, "code-base-name": "https://github.com/sathish2003-pixel/SpicKitchen.git:main", "knowledge_revision": 32, "git_revision": "9445656b422eb1d28d383086be48591773e32a8a", "revision_history": [{"32": "9445656b422eb1d28d383086be48591773e32a8a"}]}